bonsai_config/__init__.py
bonsai_config/bonsai_config.py
bonsai_config/test_bonsai_config.py
bonsai_config-0.4.5.dist-info/DESCRIPTION.rst
bonsai_config-0.4.5.dist-info/METADATA
bonsai_config-0.4.5.dist-info/RECORD
bonsai_config-0.4.5.dist-info/WHEEL
bonsai_config-0.4.5.dist-info/metadata.json
bonsai_config-0.4.5.dist-info/top_level.txt
