Metadata-Version: 2.0
Name: bonsai-config
Version: 0.4.5
Summary: A python library reading and writing bonsai configuration files
Home-page: http://github.com/BonsaiAI/bonsai-config
Author: Bonsai Engineering
Author-email: opensource@bons.ai
License: BSD
Keywords: bonsai
Platform: UNKNOWN
Classifier: Development Status :: 4 - Beta
Classifier: Intended Audience :: Developers
Classifier: Topic :: Scientific/Engineering :: Artificial Intelligence
Classifier: License :: OSI Approved :: BSD License
Classifier: Programming Language :: Python :: 2
Classifier: Programming Language :: Python :: 2.7
Classifier: Programming Language :: Python :: 3
Classifier: Programming Language :: Python :: 3.4
Classifier: Programming Language :: Python :: 3.5
Classifier: Natural Language :: English
Requires-Dist: six (>=1.10)
